[{"score":98,"score_max":100,"score_min":97,"flag":1,"level":1,"start_time":1585530000000,"end_time":1585530059999},{"score":59,"score_max":97,"score_min":26,"flag":1,"level":0,"start_time":1585530060000,"end_time":1585530119999},{"score":61,"score_max":89,"score_min":26,"flag":1,"level":0,"start_time":1585530120000,"end_time":1585530179999},{"score":83,"score_max":91,"score_min":70,"flag":1,"level":1,"start_time":1585530180000,"end_time":1585530239999},{"score":55,"score_max":69,"score_min":41,"flag":1,"level":0,"start_time":1585530240000,"end_time":1585530299999},{"score":32,"score_max":43,"score_min":13,"flag":1,"level":0,"start_time":1585530300000,"end_time":1585530359999},{"score":4,"score_max":19,"score_min":1,"flag":1,"level":0,"start_time":1585530360000,"end_time":1585530419999},{"score":83,"score_max":100,"score_min":22,"flag":1,"level":1,"start_time":1585530420000,"end_time":1585530479999},{"score":100,"score_max":100,"score_min":100,"flag":1,"level":1,"start_time":1585530480000,"end_time":1585530539999},{"score":100,"score_max":100,"score_min":100,"flag":1,"level":1,"start_time":1585530540000,"end_time":1585530599999},{"score":100,"score_max":100,"score_min":100,"flag":1,"level":1,"start_time":1585530600000,"end_time":1585530659999},{"score":100,"score_max":100,"score_min":100,"flag":1,"level":1,"start_time":1585530660000,"end_time":1585530719999},{"score":100,"score_max":100,"score_min":100,"flag":1,"level":1,"start_time":1585530720000,"end_time":1585530779999},{"score":100,"score_max":100,"score_min":100,"flag":1,"level":1,"start_time":1585530780000,"end_time":1585530839999},{"score":100,"score_max":100,"score_min":100,"flag":1,"level":1,"start_time":1585530840000,"end_time":1585530899999},{"score":100,"score_max":100,"score_min":100,"flag":1,"level":1,"start_time":1585530900000,"end_time":1585530959999},{"score":100,"score_max":100,"score_min":100,"flag":1,"level":1,"start_time":1585530960000,"end_time":1585531019999},{"score":100,"score_max":100,"score_min":100,"flag":1,"level":1,"start_time":1585531020000,"end_time":1585531079999},{"score":0,"score_max":0,"score_min":0,"flag":1,"level":0,"start_time":1585531200000,"end_time":1585531259999},{"score":1,"score_max":2,"score_min":0,"flag":1,"level":0,"start_time":1585531260000,"end_time":1585531319999},{"score":5,"score_max":22,"score_min":2,"flag":1,"level":0,"start_time":1585531320000,"end_time":1585531379999},{"score":84,"score_max":100,"score_min":24,"flag":1,"level":1,"start_time":1585531380000,"end_time":1585531439999},{"score":99,"score_max":100,"score_min":99,"flag":1,"level":1,"start_time":1585531440000,"end_time":1585531499999},{"score":97,"score_max":99,"score_min":95,"flag":1,"level":1,"start_time":1585531500000,"end_time":1585531559999},{"score":92,"score_max":99,"score_min":77,"flag":1,"level":1,"start_time":1585531560000,"end_time":1585531619999},{"score":31,"score_max":76,"score_min":4,"flag":1,"level":0,"start_time":1585531620000,"end_time":1585531679999},{"score":5,"score_max":7,"score_min":2,"flag":1,"level":0,"start_time":1585531680000,"end_time":1585531739999},{"score":11,"score_max":20,"score_min":7,"flag":1,"level":0,"start_time":1585531740000,"end_time":1585531799999},{"score":33,"score_max":58,"score_min":21,"flag":1,"level":0,"start_time":1585531800000,"end_time":1585531859999},{"score":42,"score_max":58,"score_min":27,"flag":1,"level":0,"start_time":1585531860000,"end_time":1585531919999},{"score":29,"score_max":33,"score_min":25,"flag":1,"level":0,"start_time":1585531920000,"end_time":1585531979999},{"score":16,"score_max":26,"score_min":11,"flag":1,"level":0,"start_time":1585531980000,"end_time":1585532039999},{"score":13,"score_max":17,"score_min":11,"flag":1,"level":0,"start_time":1585532040000,"end_time":1585532099999},{"score":11,"score_max":17,"score_min":10,"flag":1,"level":0,"start_time":1585532100000,"end_time":1585532159999},{"score":68,"score_max":100,"score_min":19,"flag":1,"level":0,"start_time":1585532160000,"end_time":1585532219999},{"score":11,"score_max":11,"score_min":11,"flag":1,"level":0,"start_time":1585532400000,"end_time":1585532459999},{"score":13,"score_max":16,"score_min":10,"flag":1,"level":0,"start_time":1585532460000,"end_time":1585532519999},{"score":13,"score_max":18,"score_min":10,"flag":1,"level":0,"start_time":1585532520000,"end_time":1585532579999},{"score":12,"score_max":18,"score_min":4,"flag":1,"level":0,"start_time":1585532580000,"end_time":1585532639999},{"score":9,"score_max":31,"score_min":4,"flag":1,"level":0,"start_time":1585532640000,"end_time":1585532699999},{"score":66,"score_max":93,"score_min":32,"flag":1,"level":0,"start_time":1585532700000,"end_time":1585532759999},{"score":82,"score_max":94,"score_min":48,"flag":1,"level":1,"start_time":1585532760000,"end_time":1585532819999},{"score":23,"score_max":46,"score_min":18,"flag":1,"level":0,"start_time":1585532820000,"end_time":1585532879999},{"score":42,"score_max":52,"score_min":27,"flag":1,"level":0,"start_time":1585532880000,"end_time":1585532939999},{"score":36,"score_max":49,"score_min":22,"flag":1,"level":0,"start_time":1585532940000,"end_time":1585532999999},{"score":44,"score_max":76,"score_min":22,"flag":1,"level":0,"start_time":1585533000000,"end_time":1585533059999},{"score":78,"score_max":82,"score_min":73,"flag":1,"level":1,"start_time":1585533060000,"end_time":1585533119999},{"score":74,"score_max":85,"score_min":67,"flag":1,"level":0,"start_time":1585533120000,"end_time":1585533179999},{"score":94,"score_max":97,"score_min":85,"flag":1,"level":1,"start_time":1585533180000,"end_time":1585533239999},{"score":92,"score_max":97,"score_min":88,"flag":1,"level":1,"start_time":1585533240000,"end_time":1585533299999},{"score":93,"score_max":97,"score_min":88,"flag":1,"level":1,"start_time":1585533300000,"end_time":1585533359999},{"score":73,"score_max":96,"score_min":37,"flag":1,"level":1,"start_time":1585533360000,"end_time":1585533419999},{"score":26,"score_max":36,"score_min":22,"flag":1,"level":0,"start_time":1585533420000,"end_time":1585533479999},{"score":52,"score_max":69,"score_min":31,"flag":1,"level":0,"start_time":1585533480000,"end_time":1585533539999},{"score":38,"score_max":60,"score_min":23,"flag":1,"level":0,"start_time":1585533540000,"end_time":1585533599999}]