[{"score":1,"score_max":1,"score_min":1,"flag":1,"level":0,"start_time":1592373600000,"end_time":1592373659999},{"score":0,"score_max":1,"score_min":0,"flag":1,"level":0,"start_time":1592373660000,"end_time":1592373719999},{"score":0,"score_max":0,"score_min":0,"flag":1,"level":0,"start_time":1592373720000,"end_time":1592373779999},{"score":0,"score_max":0,"score_min":0,"flag":1,"level":0,"start_time":1592373780000,"end_time":1592373839999},{"score":0,"score_max":0,"score_min":0,"flag":1,"level":0,"start_time":1592373840000,"end_time":1592373899999},{"score":0,"score_max":0,"score_min":0,"flag":1,"level":0,"start_time":1592373900000,"end_time":1592373959999},{"score":0,"score_max":0,"score_min":0,"flag":1,"level":0,"start_time":1592373960000,"end_time":1592374019999},{"score":0,"score_max":0,"score_min":0,"flag":1,"level":0,"start_time":1592374020000,"end_time":1592374079999},{"score":0,"score_max":0,"score_min":0,"flag":1,"level":0,"start_time":1592374080000,"end_time":1592374139999},{"score":0,"score_max":0,"score_min":0,"flag":1,"level":0,"start_time":1592374140000,"end_time":1592374199999},{"score":0,"score_max":0,"score_min":0,"flag":1,"level":0,"start_time":1592374200000,"end_time":1592374259999},{"score":0,"score_max":1,"score_min":0,"flag":1,"level":0,"start_time":1592374260000,"end_time":1592374319999},{"score":1,"score_max":3,"score_min":0,"flag":1,"level":0,"start_time":1592374320000,"end_time":1592374379999},{"score":0,"score_max":0,"score_min":0,"flag":1,"level":0,"start_time":1592374380000,"end_time":1592374439999},{"score":0,"score_max":0,"score_min":0,"flag":1,"level":0,"start_time":1592374440000,"end_time":1592374499999},{"score":0,"score_max":0,"score_min":0,"flag":1,"level":0,"start_time":1592374500000,"end_time":1592374559999},{"score":0,"score_max":0,"score_min":0,"flag":1,"level":0,"start_time":1592374560000,"end_time":1592374619999},{"score":0,"score_max":0,"score_min":0,"flag":1,"level":0,"start_time":1592374620000,"end_time":1592374679999},{"score":0,"score_max":0,"score_min":0,"flag":1,"level":0,"start_time":1592374680000,"end_time":1592374739999},{"score":0,"score_max":0,"score_min":0,"flag":1,"level":0,"start_time":1592374740000,"end_time":1592374799999},{"score":0,"score_max":0,"score_min":0,"flag":1,"level":0,"start_time":1592374800000,"end_time":1592374859999},{"score":0,"score_max":0,"score_min":0,"flag":1,"level":0,"start_time":1592374860000,"end_time":1592374919999},{"score":0,"score_max":0,"score_min":0,"flag":1,"level":0,"start_time":1592374920000,"end_time":1592374979999}]