[{"heart_rate":91.0,"heart_rate_max":97.0,"heart_rate_min":89.0,"start_time":1580828700000,"end_time":1580828759000},{"heart_rate":91.0,"heart_rate_max":95.0,"heart_rate_min":87.0,"start_time":1580828760000,"end_time":1580828819000},{"heart_rate":88.0,"heart_rate_max":93.0,"heart_rate_min":83.0,"start_time":1580828820000,"end_time":1580828879000},{"heart_rate":84.0,"heart_rate_max":89.0,"heart_rate_min":82.0,"start_time":1580828880000,"end_time":1580828939000},{"heart_rate":86.0,"heart_rate_max":90.0,"heart_rate_min":83.0,"start_time":1580828940000,"end_time":1580828999000},{"heart_rate":88.0,"heart_rate_max":90.0,"heart_rate_min":86.0,"start_time":1580829000000,"end_time":1580829059000},{"heart_rate":87.0,"heart_rate_max":96.0,"heart_rate_min":84.0,"start_time":1580829060000,"end_time":1580829119000},{"heart_rate":90.0,"heart_rate_max":98.0,"heart_rate_min":86.0,"start_time":1580829120000,"end_time":1580829179000},{"heart_rate":90.0,"heart_rate_max":96.0,"heart_rate_min":85.0,"start_time":1580829180000,"end_time":1580829239000},{"heart_rate":87.0,"heart_rate_max":90.0,"heart_rate_min":84.0,"start_time":1580829240000,"end_time":1580829299000},{"heart_rate":86.0,"heart_rate_max":90.0,"heart_rate_min":83.0,"start_time":1580829300000,"end_time":1580829359000},{"heart_rate":89.0,"heart_rate_max":94.0,"heart_rate_min":86.0,"start_time":1580829360000,"end_time":1580829419000},{"heart_rate":90.0,"heart_rate_max":98.0,"heart_rate_min":86.0,"start_time":1580829420000,"end_time":1580829479000},{"heart_rate":88.0,"heart_rate_max":98.0,"heart_rate_min":84.0,"start_time":1580829480000,"end_time":1580829539000},{"heart_rate":78.0,"heart_rate_max":81.0,"heart_rate_min":75.0,"start_time":1580829540000,"end_time":1580829599000},{"heart_rate":76.0,"heart_rate_max":84.0,"heart_rate_min":64.0,"start_time":1580829600000,"end_time":1580829659000},{"heart_rate":84.0,"heart_rate_max":84.0,"heart_rate_min":84.0,"start_time":1580829660000,"end_time":1580829719000},{"heart_rate":84.0,"heart_rate_max":84.0,"heart_rate_min":84.0,"start_time":1580829720000,"end_time":1580829779000},{"heart_rate":84.0,"heart_rate_max":84.0,"heart_rate_min":84.0,"start_time":1580829780000,"end_time":1580829839000},{"heart_rate":84.0,"heart_rate_max":84.0,"heart_rate_min":84.0,"start_time":1580829840000,"end_time":1580829899000},{"heart_rate":84.0,"heart_rate_max":84.0,"heart_rate_min":84.0,"start_time":1580829900000,"end_time":1580829959000},{"heart_rate":84.0,"heart_rate_max":84.0,"heart_rate_min":84.0,"start_time":1580829960000,"end_time":1580830019000},{"heart_rate":84.0,"heart_rate_max":84.0,"heart_rate_min":84.0,"start_time":1580830020000,"end_time":1580830079000},{"heart_rate":84.0,"heart_rate_max":84.0,"heart_rate_min":84.0,"start_time":1580830080000,"end_time":1580830139000},{"heart_rate":84.0,"heart_rate_max":84.0,"heart_rate_min":84.0,"start_time":1580830140000,"end_time":1580830199000},{"heart_rate":84.0,"heart_rate_max":84.0,"heart_rate_min":84.0,"start_time":1580830200000,"end_time":1580830259000}]