[{"heart_rate":84.0,"heart_rate_max":89.0,"heart_rate_min":80.0,"start_time":1566867600000,"end_time":1566867659000},{"heart_rate":86.0,"heart_rate_max":91.0,"heart_rate_min":83.0,"start_time":1566867660000,"end_time":1566867719000},{"heart_rate":97.0,"heart_rate_max":98.0,"heart_rate_min":97.0,"start_time":1566867720000,"end_time":1566867779000},{"heart_rate":88.0,"heart_rate_max":96.0,"heart_rate_min":77.0,"start_time":1566867780000,"end_time":1566867839000},{"heart_rate":86.0,"heart_rate_max":91.0,"heart_rate_min":80.0,"start_time":1566867840000,"end_time":1566867899000},{"heart_rate":85.0,"heart_rate_max":89.0,"heart_rate_min":80.0,"start_time":1566867900000,"end_time":1566867959000},{"heart_rate":86.0,"heart_rate_max":89.0,"heart_rate_min":83.0,"start_time":1566867960000,"end_time":1566868019000},{"heart_rate":83.0,"heart_rate_max":95.0,"heart_rate_min":73.0,"start_time":1566868020000,"end_time":1566868079000},{"heart_rate":93.0,"heart_rate_max":99.0,"heart_rate_min":84.0,"start_time":1566868080000,"end_time":1566868139000},{"heart_rate":98.0,"heart_rate_max":104.0,"heart_rate_min":91.0,"start_time":1566868140000,"end_time":1566868199000},{"heart_rate":107.0,"heart_rate_max":114.0,"heart_rate_min":101.0,"start_time":1566868200000,"end_time":1566868259000},{"heart_rate":98.0,"heart_rate_max":117.0,"heart_rate_min":83.0,"start_time":1566868260000,"end_time":1566868319000},{"heart_rate":91.0,"heart_rate_max":98.0,"heart_rate_min":81.0,"start_time":1566868320000,"end_time":1566868379000},{"heart_rate":86.0,"heart_rate_max":89.0,"heart_rate_min":80.0,"start_time":1566868380000,"end_time":1566868439000},{"heart_rate":87.0,"heart_rate_max":94.0,"heart_rate_min":84.0,"start_time":1566868440000,"end_time":1566868499000},{"heart_rate":91.0,"heart_rate_max":97.0,"heart_rate_min":86.0,"start_time":1566868500000,"end_time":1566868559000},{"heart_rate":82.0,"heart_rate_max":89.0,"heart_rate_min":78.0,"start_time":1566868560000,"end_time":1566868619000},{"heart_rate":92.0,"heart_rate_max":110.0,"heart_rate_min":85.0,"start_time":1566868620000,"end_time":1566868679000},{"heart_rate":87.0,"heart_rate_max":96.0,"heart_rate_min":81.0,"start_time":1566868680000,"end_time":1566868739000},{"heart_rate":87.0,"heart_rate_max":95.0,"heart_rate_min":76.0,"start_time":1566868740000,"end_time":1566868799000},{"heart_rate":95.0,"heart_rate_max":106.0,"heart_rate_min":83.0,"start_time":1566868800000,"end_time":1566868859000},{"heart_rate":98.0,"heart_rate_max":103.0,"heart_rate_min":92.0,"start_time":1566868860000,"end_time":1566868919000},{"heart_rate":91.0,"heart_rate_max":106.0,"heart_rate_min":70.0,"start_time":1566868920000,"end_time":1566868979000},{"heart_rate":89.0,"heart_rate_max":100.0,"heart_rate_min":78.0,"start_time":1566868980000,"end_time":1566869039000},{"heart_rate":95.0,"heart_rate_max":98.0,"heart_rate_min":91.0,"start_time":1566869040000,"end_time":1566869099000},{"heart_rate":87.0,"heart_rate_max":96.0,"heart_rate_min":72.0,"start_time":1566869100000,"end_time":1566869159000},{"heart_rate":81.0,"heart_rate_max":90.0,"heart_rate_min":73.0,"start_time":1566869160000,"end_time":1566869219000},{"heart_rate":78.0,"heart_rate_max":84.0,"heart_rate_min":73.0,"start_time":1566869220000,"end_time":1566869279000},{"heart_rate":83.0,"heart_rate_max":90.0,"heart_rate_min":76.0,"start_time":1566869280000,"end_time":1566869339000},{"heart_rate":94.0,"heart_rate_max":99.0,"heart_rate_min":88.0,"start_time":1566869340000,"end_time":1566869399000},{"heart_rate":96.0,"heart_rate_max":99.0,"heart_rate_min":93.0,"start_time":1566869400000,"end_time":1566869459000},{"heart_rate":95.0,"heart_rate_max":99.0,"heart_rate_min":92.0,"start_time":1566869460000,"end_time":1566869519000},{"heart_rate":99.0,"heart_rate_max":104.0,"heart_rate_min":96.0,"start_time":1566869520000,"end_time":1566869579000},{"heart_rate":105.0,"heart_rate_max":109.0,"heart_rate_min":103.0,"start_time":1566869580000,"end_time":1566869639000},{"heart_rate":115.0,"heart_rate_max":119.0,"heart_rate_min":107.0,"start_time":1566869640000,"end_time":1566869699000},{"heart_rate":119.0,"heart_rate_max":121.0,"heart_rate_min":119.0,"start_time":1566869700000,"end_time":1566869759000},{"heart_rate":120.0,"heart_rate_max":122.0,"heart_rate_min":117.0,"start_time":1566869760000,"end_time":1566869819000},{"heart_rate":119.0,"heart_rate_max":122.0,"heart_rate_min":117.0,"start_time":1566869820000,"end_time":1566869879000},{"heart_rate":121.0,"heart_rate_max":123.0,"heart_rate_min":119.0,"start_time":1566869880000,"end_time":1566869939000},{"heart_rate":122.0,"heart_rate_max":126.0,"heart_rate_min":120.0,"start_time":1566869940000,"end_time":1566869999000},{"heart_rate":126.0,"heart_rate_max":132.0,"heart_rate_min":123.0,"start_time":1566870000000,"end_time":1566870059000},{"heart_rate":121.0,"heart_rate_max":122.0,"heart_rate_min":120.0,"start_time":1566870060000,"end_time":1566870119000},{"heart_rate":123.0,"heart_rate_max":138.0,"heart_rate_min":118.0,"start_time":1566870120000,"end_time":1566870179000},{"heart_rate":138.0,"heart_rate_max":143.0,"heart_rate_min":134.0,"start_time":1566870180000,"end_time":1566870239000},{"heart_rate":144.0,"heart_rate_max":159.0,"heart_rate_min":143.0,"start_time":1566870240000,"end_time":1566870299000},{"heart_rate":139.0,"heart_rate_max":139.0,"heart_rate_min":139.0,"start_time":1566870780000,"end_time":1566870839000},{"heart_rate":136.0,"heart_rate_max":139.0,"heart_rate_min":134.0,"start_time":1566870840000,"end_time":1566870899000},{"heart_rate":136.0,"heart_rate_max":139.0,"heart_rate_min":133.0,"start_time":1566870900000,"end_time":1566870959000},{"heart_rate":135.0,"heart_rate_max":137.0,"heart_rate_min":134.0,"start_time":1566870960000,"end_time":1566871019000},{"heart_rate":136.0,"heart_rate_max":139.0,"heart_rate_min":134.0,"start_time":1566871020000,"end_time":1566871079000},{"heart_rate":134.0,"heart_rate_max":137.0,"heart_rate_min":131.0,"start_time":1566871080000,"end_time":1566871139000}]