[{"score":0,"score_max":0,"score_min":0,"flag":1,"level":0,"start_time":1591383600000,"end_time":1591383659999},{"score":0,"score_max":0,"score_min":0,"flag":1,"level":0,"start_time":1591383660000,"end_time":1591383719999},{"score":0,"score_max":0,"score_min":0,"flag":1,"level":0,"start_time":1591383720000,"end_time":1591383779999},{"score":0,"score_max":0,"score_min":0,"flag":1,"level":0,"start_time":1591383780000,"end_time":1591383839999},{"score":0,"score_max":0,"score_min":0,"flag":1,"level":0,"start_time":1591383840000,"end_time":1591383899999},{"score":0,"score_max":0,"score_min":0,"flag":1,"level":0,"start_time":1591383900000,"end_time":1591383959999},{"score":0,"score_max":0,"score_min":0,"flag":1,"level":0,"start_time":1591383960000,"end_time":1591384019999},{"score":0,"score_max":0,"score_min":0,"flag":1,"level":0,"start_time":1591384020000,"end_time":1591384079999},{"score":0,"score_max":0,"score_min":0,"flag":1,"level":0,"start_time":1591384080000,"end_time":1591384139999},{"score":0,"score_max":0,"score_min":0,"flag":1,"level":0,"start_time":1591384140000,"end_time":1591384199999},{"score":0,"score_max":0,"score_min":0,"flag":1,"level":0,"start_time":1591384200000,"end_time":1591384259999},{"score":0,"score_max":0,"score_min":0,"flag":1,"level":0,"start_time":1591384260000,"end_time":1591384319999},{"score":0,"score_max":0,"score_min":0,"flag":1,"level":0,"start_time":1591384320000,"end_time":1591384379999},{"score":0,"score_max":0,"score_min":0,"flag":1,"level":0,"start_time":1591384380000,"end_time":1591384439999},{"score":0,"score_max":0,"score_min":0,"flag":1,"level":0,"start_time":1591384440000,"end_time":1591384499999},{"score":0,"score_max":0,"score_min":0,"flag":1,"level":0,"start_time":1591384500000,"end_time":1591384559999},{"score":0,"score_max":0,"score_min":0,"flag":1,"level":0,"start_time":1591384560000,"end_time":1591384619999},{"score":0,"score_max":0,"score_min":0,"flag":1,"level":0,"start_time":1591384620000,"end_time":1591384679999},{"score":0,"score_max":0,"score_min":0,"flag":1,"level":0,"start_time":1591384680000,"end_time":1591384739999}]