[{"heart_rate":123.0,"heart_rate_max":124.0,"heart_rate_min":123.0,"start_time":1571691600000,"end_time":1571691659000},{"heart_rate":121.0,"heart_rate_max":123.0,"heart_rate_min":119.0,"start_time":1571691660000,"end_time":1571691719000},{"heart_rate":124.0,"heart_rate_max":132.0,"heart_rate_min":121.0,"start_time":1571691720000,"end_time":1571691779000},{"heart_rate":129.0,"heart_rate_max":130.0,"heart_rate_min":129.0,"start_time":1571692080000,"end_time":1571692139000},{"heart_rate":125.0,"heart_rate_max":129.0,"heart_rate_min":121.0,"start_time":1571692140000,"end_time":1571692199000},{"heart_rate":118.0,"heart_rate_max":123.0,"heart_rate_min":114.0,"start_time":1571692200000,"end_time":1571692259000},{"heart_rate":113.0,"heart_rate_max":118.0,"heart_rate_min":110.0,"start_time":1571692260000,"end_time":1571692319000},{"heart_rate":112.0,"heart_rate_max":115.0,"heart_rate_min":110.0,"start_time":1571692320000,"end_time":1571692379000},{"heart_rate":110.0,"heart_rate_max":115.0,"heart_rate_min":108.0,"start_time":1571692380000,"end_time":1571692439000},{"heart_rate":105.0,"heart_rate_max":112.0,"heart_rate_min":102.0,"start_time":1571692440000,"end_time":1571692499000},{"heart_rate":107.0,"heart_rate_max":110.0,"heart_rate_min":105.0,"start_time":1571692500000,"end_time":1571692559000},{"heart_rate":106.0,"heart_rate_max":112.0,"heart_rate_min":101.0,"start_time":1571692560000,"end_time":1571692619000},{"heart_rate":109.0,"heart_rate_max":112.0,"heart_rate_min":108.0,"start_time":1571692620000,"end_time":1571692679000},{"heart_rate":109.0,"heart_rate_max":114.0,"heart_rate_min":104.0,"start_time":1571692680000,"end_time":1571692739000},{"heart_rate":103.0,"heart_rate_max":106.0,"heart_rate_min":100.0,"start_time":1571692740000,"end_time":1571692799000},{"heart_rate":105.0,"heart_rate_max":108.0,"heart_rate_min":103.0,"start_time":1571692800000,"end_time":1571692859000},{"heart_rate":96.0,"heart_rate_max":110.0,"heart_rate_min":89.0,"start_time":1571692860000,"end_time":1571692919000},{"heart_rate":102.0,"heart_rate_max":107.0,"heart_rate_min":94.0,"start_time":1571692920000,"end_time":1571692979000},{"heart_rate":100.0,"heart_rate_max":107.0,"heart_rate_min":93.0,"start_time":1571692980000,"end_time":1571693039000},{"heart_rate":107.0,"heart_rate_max":114.0,"heart_rate_min":96.0,"start_time":1571693040000,"end_time":1571693099000},{"heart_rate":106.0,"heart_rate_max":112.0,"heart_rate_min":97.0,"start_time":1571693100000,"end_time":1571693159000},{"heart_rate":104.0,"heart_rate_max":120.0,"heart_rate_min":88.0,"start_time":1571693160000,"end_time":1571693219000},{"heart_rate":118.0,"heart_rate_max":119.0,"heart_rate_min":117.0,"start_time":1571693220000,"end_time":1571693279000},{"heart_rate":115.0,"heart_rate_max":119.0,"heart_rate_min":114.0,"start_time":1571693280000,"end_time":1571693339000},{"heart_rate":103.0,"heart_rate_max":125.0,"heart_rate_min":91.0,"start_time":1571693340000,"end_time":1571693399000},{"heart_rate":122.0,"heart_rate_max":126.0,"heart_rate_min":118.0,"start_time":1571693400000,"end_time":1571693459000},{"heart_rate":123.0,"heart_rate_max":127.0,"heart_rate_min":120.0,"start_time":1571693460000,"end_time":1571693519000},{"heart_rate":90.0,"heart_rate_max":130.0,"heart_rate_min":65.0,"start_time":1571693520000,"end_time":1571693579000},{"heart_rate":74.0,"heart_rate_max":81.0,"heart_rate_min":65.0,"start_time":1571693580000,"end_time":1571693639000},{"heart_rate":88.0,"heart_rate_max":97.0,"heart_rate_min":78.0,"start_time":1571693640000,"end_time":1571693699000},{"heart_rate":91.0,"heart_rate_max":95.0,"heart_rate_min":88.0,"start_time":1571693700000,"end_time":1571693759000},{"heart_rate":92.0,"heart_rate_max":101.0,"heart_rate_min":85.0,"start_time":1571693760000,"end_time":1571693819000},{"heart_rate":86.0,"heart_rate_max":98.0,"heart_rate_min":71.0,"start_time":1571693820000,"end_time":1571693879000},{"heart_rate":85.0,"heart_rate_max":91.0,"heart_rate_min":83.0,"start_time":1571693880000,"end_time":1571693939000},{"heart_rate":93.0,"heart_rate_max":101.0,"heart_rate_min":90.0,"start_time":1571693940000,"end_time":1571693999000},{"heart_rate":104.0,"heart_rate_max":109.0,"heart_rate_min":98.0,"start_time":1571694000000,"end_time":1571694059000},{"heart_rate":111.0,"heart_rate_max":115.0,"heart_rate_min":110.0,"start_time":1571694060000,"end_time":1571694119000},{"heart_rate":113.0,"heart_rate_max":118.0,"heart_rate_min":110.0,"start_time":1571694120000,"end_time":1571694179000},{"heart_rate":103.0,"heart_rate_max":118.0,"heart_rate_min":85.0,"start_time":1571694180000,"end_time":1571694239000},{"heart_rate":91.0,"heart_rate_max":95.0,"heart_rate_min":89.0,"start_time":1571694240000,"end_time":1571694299000},{"heart_rate":100.0,"heart_rate_max":109.0,"heart_rate_min":94.0,"start_time":1571694300000,"end_time":1571694359000},{"heart_rate":116.0,"heart_rate_max":121.0,"heart_rate_min":108.0,"start_time":1571694360000,"end_time":1571694419000},{"heart_rate":128.0,"heart_rate_max":135.0,"heart_rate_min":119.0,"start_time":1571694420000,"end_time":1571694479000},{"heart_rate":133.0,"heart_rate_max":138.0,"heart_rate_min":130.0,"start_time":1571694480000,"end_time":1571694539000},{"heart_rate":137.0,"heart_rate_max":142.0,"heart_rate_min":134.0,"start_time":1571694540000,"end_time":1571694599000},{"heart_rate":145.0,"heart_rate_max":154.0,"heart_rate_min":139.0,"start_time":1571694600000,"end_time":1571694659000}]