[{"heart_rate":60.0,"heart_rate_max":63.0,"heart_rate_min":59.0,"start_time":1586008800000,"end_time":1586008859000},{"heart_rate":60.0,"heart_rate_max":62.0,"heart_rate_min":59.0,"start_time":1586008860000,"end_time":1586008919000},{"heart_rate":60.0,"heart_rate_max":62.0,"heart_rate_min":58.0,"start_time":1586008920000,"end_time":1586008979000},{"heart_rate":60.0,"heart_rate_max":62.0,"heart_rate_min":59.0,"start_time":1586008980000,"end_time":1586009039000},{"heart_rate":59.0,"heart_rate_max":61.0,"heart_rate_min":57.0,"start_time":1586009040000,"end_time":1586009099000},{"heart_rate":63.0,"heart_rate_max":73.0,"heart_rate_min":59.0,"start_time":1586009100000,"end_time":1586009159000},{"heart_rate":51.0,"heart_rate_max":58.0,"heart_rate_min":46.0,"start_time":1586009160000,"end_time":1586009219000},{"heart_rate":49.0,"heart_rate_max":53.0,"heart_rate_min":46.0,"start_time":1586009220000,"end_time":1586009279000},{"heart_rate":50.0,"heart_rate_max":53.0,"heart_rate_min":48.0,"start_time":1586009280000,"end_time":1586009339000},{"heart_rate":50.0,"heart_rate_max":54.0,"heart_rate_min":48.0,"start_time":1586009340000,"end_time":1586009399000},{"heart_rate":51.0,"heart_rate_max":56.0,"heart_rate_min":49.0,"start_time":1586009400000,"end_time":1586009459000},{"heart_rate":53.0,"heart_rate_max":59.0,"heart_rate_min":50.0,"start_time":1586009460000,"end_time":1586009519000},{"heart_rate":54.0,"heart_rate_max":60.0,"heart_rate_min":52.0,"start_time":1586009520000,"end_time":1586009579000},{"heart_rate":54.0,"heart_rate_max":62.0,"heart_rate_min":51.0,"start_time":1586009580000,"end_time":1586009639000},{"heart_rate":57.0,"heart_rate_max":66.0,"heart_rate_min":52.0,"start_time":1586009640000,"end_time":1586009699000},{"heart_rate":61.0,"heart_rate_max":65.0,"heart_rate_min":57.0,"start_time":1586009700000,"end_time":1586009759000},{"heart_rate":61.0,"heart_rate_max":70.0,"heart_rate_min":55.0,"start_time":1586009760000,"end_time":1586009819000},{"heart_rate":60.0,"heart_rate_max":65.0,"heart_rate_min":58.0,"start_time":1586009820000,"end_time":1586009879000},{"heart_rate":64.0,"heart_rate_max":72.0,"heart_rate_min":61.0,"start_time":1586009880000,"end_time":1586009939000},{"heart_rate":59.0,"heart_rate_max":65.0,"heart_rate_min":56.0,"start_time":1586009940000,"end_time":1586009999000},{"heart_rate":58.0,"heart_rate_max":65.0,"heart_rate_min":52.0,"start_time":1586010000000,"end_time":1586010059000},{"heart_rate":56.0,"heart_rate_max":60.0,"heart_rate_min":53.0,"start_time":1586010060000,"end_time":1586010119000},{"heart_rate":61.0,"heart_rate_max":66.0,"heart_rate_min":57.0,"start_time":1586010120000,"end_time":1586010179000},{"heart_rate":63.0,"heart_rate_max":68.0,"heart_rate_min":60.0,"start_time":1586010180000,"end_time":1586010239000},{"heart_rate":59.0,"heart_rate_max":68.0,"heart_rate_min":55.0,"start_time":1586010240000,"end_time":1586010299000},{"heart_rate":53.0,"heart_rate_max":66.0,"heart_rate_min":48.0,"start_time":1586010300000,"end_time":1586010359000},{"heart_rate":51.0,"heart_rate_max":58.0,"heart_rate_min":48.0,"start_time":1586010360000,"end_time":1586010419000},{"heart_rate":53.0,"heart_rate_max":57.0,"heart_rate_min":49.0,"start_time":1586010420000,"end_time":1586010479000},{"heart_rate":53.0,"heart_rate_max":57.0,"heart_rate_min":49.0,"start_time":1586010480000,"end_time":1586010539000},{"heart_rate":53.0,"heart_rate_max":60.0,"heart_rate_min":46.0,"start_time":1586010540000,"end_time":1586010599000},{"heart_rate":52.0,"heart_rate_max":57.0,"heart_rate_min":48.0,"start_time":1586010600000,"end_time":1586010659000},{"heart_rate":56.0,"heart_rate_max":60.0,"heart_rate_min":53.0,"start_time":1586010660000,"end_time":1586010719000},{"heart_rate":59.0,"heart_rate_max":62.0,"heart_rate_min":55.0,"start_time":1586010720000,"end_time":1586010779000},{"heart_rate":61.0,"heart_rate_max":65.0,"heart_rate_min":59.0,"start_time":1586010780000,"end_time":1586010839000},{"heart_rate":57.0,"heart_rate_max":63.0,"heart_rate_min":53.0,"start_time":1586010840000,"end_time":1586010899000},{"heart_rate":56.0,"heart_rate_max":59.0,"heart_rate_min":53.0,"start_time":1586010900000,"end_time":1586010959000},{"heart_rate":53.0,"heart_rate_max":58.0,"heart_rate_min":50.0,"start_time":1586010960000,"end_time":1586011019000},{"heart_rate":57.0,"heart_rate_max":63.0,"heart_rate_min":51.0,"start_time":1586011020000,"end_time":1586011079000},{"heart_rate":51.0,"heart_rate_max":56.0,"heart_rate_min":48.0,"start_time":1586011080000,"end_time":1586011139000},{"heart_rate":53.0,"heart_rate_max":57.0,"heart_rate_min":51.0,"start_time":1586011140000,"end_time":1586011199000},{"heart_rate":58.0,"heart_rate_max":65.0,"heart_rate_min":51.0,"start_time":1586011200000,"end_time":1586011259000},{"heart_rate":51.0,"heart_rate_max":56.0,"heart_rate_min":48.0,"start_time":1586011260000,"end_time":1586011319000},{"heart_rate":57.0,"heart_rate_max":60.0,"heart_rate_min":55.0,"start_time":1586011320000,"end_time":1586011379000},{"heart_rate":59.0,"heart_rate_max":63.0,"heart_rate_min":57.0,"start_time":1586011380000,"end_time":1586011439000},{"heart_rate":57.0,"heart_rate_max":61.0,"heart_rate_min":54.0,"start_time":1586011440000,"end_time":1586011499000},{"heart_rate":56.0,"heart_rate_max":57.0,"heart_rate_min":56.0,"start_time":1586011500000,"end_time":1586011559000},{"heart_rate":58.0,"heart_rate_max":62.0,"heart_rate_min":56.0,"start_time":1586011560000,"end_time":1586011619000},{"heart_rate":57.0,"heart_rate_max":60.0,"heart_rate_min":55.0,"start_time":1586011620000,"end_time":1586011679000},{"heart_rate":58.0,"heart_rate_max":62.0,"heart_rate_min":55.0,"start_time":1586011680000,"end_time":1586011739000},{"heart_rate":57.0,"heart_rate_max":60.0,"heart_rate_min":54.0,"start_time":1586011740000,"end_time":1586011799000},{"heart_rate":59.0,"heart_rate_max":63.0,"heart_rate_min":58.0,"start_time":1586011800000,"end_time":1586011859000},{"heart_rate":58.0,"heart_rate_max":61.0,"heart_rate_min":55.0,"start_time":1586011860000,"end_time":1586011919000},{"heart_rate":59.0,"heart_rate_max":62.0,"heart_rate_min":57.0,"start_time":1586011920000,"end_time":1586011979000},{"heart_rate":57.0,"heart_rate_max":61.0,"heart_rate_min":54.0,"start_time":1586011980000,"end_time":1586012039000},{"heart_rate":62.0,"heart_rate_max":72.0,"heart_rate_min":55.0,"start_time":1586012040000,"end_time":1586012099000},{"heart_rate":52.0,"heart_rate_max":58.0,"heart_rate_min":47.0,"start_time":1586012100000,"end_time":1586012159000},{"heart_rate":52.0,"heart_rate_max":55.0,"heart_rate_min":50.0,"start_time":1586012160000,"end_time":1586012219000},{"heart_rate":52.0,"heart_rate_max":55.0,"heart_rate_min":50.0,"start_time":1586012220000,"end_time":1586012279000},{"heart_rate":51.0,"heart_rate_max":56.0,"heart_rate_min":49.0,"start_time":1586012280000,"end_time":1586012339000},{"heart_rate":50.0,"heart_rate_max":57.0,"heart_rate_min":48.0,"start_time":1586012340000,"end_time":1586012399000}]