[{"score":17,"score_max":17,"score_min":17,"flag":1,"level":0,"start_time":1586035680000,"end_time":1586035739999},{"score":17,"score_max":20,"score_min":17,"flag":1,"level":0,"start_time":1586035740000,"end_time":1586035799999},{"score":50,"score_max":87,"score_min":19,"flag":1,"level":0,"start_time":1586035800000,"end_time":1586035859999},{"score":94,"score_max":99,"score_min":88,"flag":1,"level":1,"start_time":1586035860000,"end_time":1586035919999},{"score":99,"score_max":100,"score_min":99,"flag":1,"level":1,"start_time":1586035920000,"end_time":1586035979999},{"score":0,"score_max":0,"score_min":0,"flag":1,"level":0,"start_time":1586036460000,"end_time":1586036519999},{"score":2,"score_max":4,"score_min":0,"flag":1,"level":0,"start_time":1586036520000,"end_time":1586036579999},{"score":6,"score_max":10,"score_min":4,"flag":1,"level":0,"start_time":1586036580000,"end_time":1586036639999},{"score":1,"score_max":6,"score_min":0,"flag":1,"level":0,"start_time":1586036640000,"end_time":1586036699999},{"score":0,"score_max":0,"score_min":0,"flag":1,"level":0,"start_time":1586036700000,"end_time":1586036759999},{"score":27,"score_max":86,"score_min":0,"flag":1,"level":0,"start_time":1586036760000,"end_time":1586036819999},{"score":97,"score_max":100,"score_min":87,"flag":1,"level":1,"start_time":1586036820000,"end_time":1586036879999},{"score":100,"score_max":100,"score_min":100,"flag":1,"level":1,"start_time":1586036880000,"end_time":1586036939999},{"score":99,"score_max":100,"score_min":98,"flag":1,"level":1,"start_time":1586036940000,"end_time":1586036999999},{"score":90,"score_max":98,"score_min":76,"flag":1,"level":1,"start_time":1586037000000,"end_time":1586037059999},{"score":84,"score_max":90,"score_min":76,"flag":1,"level":1,"start_time":1586037060000,"end_time":1586037119999},{"score":82,"score_max":92,"score_min":77,"flag":1,"level":1,"start_time":1586037120000,"end_time":1586037179999},{"score":92,"score_max":96,"score_min":84,"flag":1,"level":1,"start_time":1586037180000,"end_time":1586037239999},{"score":67,"score_max":83,"score_min":62,"flag":1,"level":0,"start_time":1586037240000,"end_time":1586037299999},{"score":78,"score_max":83,"score_min":70,"flag":1,"level":1,"start_time":1586037300000,"end_time":1586037359999},{"score":93,"score_max":98,"score_min":83,"flag":1,"level":1,"start_time":1586037360000,"end_time":1586037419999},{"score":81,"score_max":97,"score_min":60,"flag":1,"level":1,"start_time":1586037420000,"end_time":1586037479999},{"score":38,"score_max":59,"score_min":31,"flag":1,"level":0,"start_time":1586037480000,"end_time":1586037539999},{"score":87,"score_max":99,"score_min":49,"flag":1,"level":1,"start_time":1586037540000,"end_time":1586037599999}]