[{"score":81,"score_max":90,"score_min":65,"flag":1,"level":1,"start_time":1582660800000,"end_time":1582660859999},{"score":44,"score_max":64,"score_min":19,"flag":1,"level":0,"start_time":1582660860000,"end_time":1582660919999},{"score":29,"score_max":60,"score_min":16,"flag":1,"level":0,"start_time":1582660920000,"end_time":1582660979999},{"score":79,"score_max":87,"score_min":61,"flag":1,"level":1,"start_time":1582660980000,"end_time":1582661039999},{"score":94,"score_max":99,"score_min":87,"flag":1,"level":1,"start_time":1582661040000,"end_time":1582661099999},{"score":94,"score_max":99,"score_min":76,"flag":1,"level":1,"start_time":1582661100000,"end_time":1582661159999},{"score":76,"score_max":91,"score_min":65,"flag":1,"level":0,"start_time":1582661160000,"end_time":1582661219999},{"score":97,"score_max":100,"score_min":92,"flag":1,"level":1,"start_time":1582661220000,"end_time":1582661279999},{"score":100,"score_max":100,"score_min":100,"flag":1,"level":1,"start_time":1582661280000,"end_time":1582661339999},{"score":6,"score_max":9,"score_min":4,"flag":1,"level":0,"start_time":1582661820000,"end_time":1582661879999},{"score":12,"score_max":15,"score_min":10,"flag":1,"level":0,"start_time":1582661880000,"end_time":1582661939999},{"score":13,"score_max":16,"score_min":11,"flag":1,"level":0,"start_time":1582662240000,"end_time":1582662299999},{"score":13,"score_max":16,"score_min":11,"flag":1,"level":0,"start_time":1582662300000,"end_time":1582662359999},{"score":21,"score_max":37,"score_min":11,"flag":1,"level":0,"start_time":1582662360000,"end_time":1582662419999},{"score":30,"score_max":39,"score_min":20,"flag":1,"level":0,"start_time":1582662420000,"end_time":1582662479999},{"score":55,"score_max":89,"score_min":21,"flag":1,"level":0,"start_time":1582662480000,"end_time":1582662539999},{"score":97,"score_max":100,"score_min":89,"flag":1,"level":1,"start_time":1582662540000,"end_time":1582662599999},{"score":100,"score_max":100,"score_min":100,"flag":1,"level":1,"start_time":1582662600000,"end_time":1582662659999},{"score":1,"score_max":8,"score_min":0,"flag":1,"level":0,"start_time":1582663500000,"end_time":1582663559999},{"score":45,"score_max":78,"score_min":9,"flag":1,"level":0,"start_time":1582663560000,"end_time":1582663619999},{"score":88,"score_max":96,"score_min":78,"flag":1,"level":1,"start_time":1582663620000,"end_time":1582663679999},{"score":97,"score_max":99,"score_min":96,"flag":1,"level":1,"start_time":1582663680000,"end_time":1582663739999},{"score":0,"score_max":0,"score_min":0,"flag":1,"level":0,"start_time":1582663800000,"end_time":1582663859999},{"score":3,"score_max":7,"score_min":0,"flag":1,"level":0,"start_time":1582663860000,"end_time":1582663919999},{"score":1,"score_max":5,"score_min":0,"flag":1,"level":0,"start_time":1582663920000,"end_time":1582663979999},{"score":2,"score_max":6,"score_min":0,"flag":1,"level":0,"start_time":1582663980000,"end_time":1582664039999},{"score":1,"score_max":3,"score_min":0,"flag":1,"level":0,"start_time":1582664040000,"end_time":1582664099999},{"score":45,"score_max":98,"score_min":1,"flag":1,"level":0,"start_time":1582664100000,"end_time":1582664159999},{"score":99,"score_max":100,"score_min":99,"flag":1,"level":1,"start_time":1582664160000,"end_time":1582664219999}]