[{"calorie":0.0,"count":0,"distance":0.0,"speed":0.0},{"calorie":0.0,"count":0,"distance":0.0,"speed":0.0},{"calorie":0.0,"count":0,"distance":0.0,"speed":0.0},{"calorie":0.0,"count":0,"distance":0.0,"speed":0.0},{"calorie":0.0,"count":0,"distance":0.0,"speed":0.0},{"calorie":0.0,"count":0,"distance":0.0,"speed":0.0},{"calorie":0.0,"count":0,"distance":0.0,"speed":0.0},{"calorie":0.0,"count":0,"distance":0.0,"speed":0.0},{"calorie":0.0,"count":0,"distance":0.0,"speed":0.0},{"calorie":0.0,"count":0,"distance":0.0,"speed":0.0},{"calorie":0.0,"count":0,"distance":0.0,"speed":0.0},{"calorie":0.0,"count":0,"distance":0.0,"speed":0.0},{"calorie":0.0,"count":0,"distance":0.0,"speed":0.0},{"calorie":0.0,"count":0,"distance":0.0,"speed":0.0},{"calorie":0.0,"count":0,"distance":0.0,"speed":0.0},{"calorie":0.0,"count":0,"distance":0.0,"speed":0.0},{"calorie":0.0,"count":0,"distance":0.0,"speed":0.0},{"calorie":0.0,"count":0,"distance":0.0,"speed":0.0},{"calorie":0.0,"count":0,"distance":0.0,"speed":0.0},{"calorie":0.0,"count":0,"distance":0.0,"speed":0.0},{"calorie":0.0,"count":0,"distance":0.0,"speed":0.0},{"calorie":0.0,"count":0,"distance":0.0,"speed":0.0},{"calorie":0.0,"count":0,"distance":0.0,"speed":0.0},{"calorie":0.0,"count":0,"distance":0.0,"speed":0.0},{"calorie":0.0,"count":0,"distance":0.0,"speed":0.0},{"calorie":0.0,"count":0,"distance":0.0,"speed":0.0},{"calorie":0.0,"count":0,"distance":0.0,"speed":0.0},{"calorie":0.0,"count":0,"distance":0.0,"speed":0.0},{"calorie":0.0,"count":0,"distance":0.0,"speed":0.0},{"calorie":0.0,"count":0,"distance":0.0,"speed":0.0},{"calorie":0.0,"count":0,"distance":0.0,"speed":0.0},{"calorie":0.0,"count":0,"distance":0.0,"speed":0.0},{"calorie":0.0,"count":0,"distance":0.0,"speed":0.0},{"calorie":0.0,"count":0,"distance":0.0,"speed":0.0},{"calorie":0.0,"count":0,"distance":0.0,"speed":0.0},{"calorie":0.0,"count":0,"distance":0.0,"speed":0.0},{"calorie":2.409999966621399,"count":66,"distance":50.1299991607666,"speed":5.081960678100586},{"calorie":0.0,"count":0,"distance":0.0,"speed":0.0},{"calorie":2.0900000035762787,"count":54,"distance":38.9399995803833,"speed":4.973167896270752},{"calorie":2.7900000512599945,"count":69,"distance":55.010000228881836,"speed":5.281669616699219},{"calorie":3.2299997806549072,"count":95,"distance":69.62999534606934,"speed":5.532557964324951},{"calorie":9.42999991774559,"count":271,"distance":211.56000232696533,"speed":5.425089359283447},{"calorie":0.0,"count":0,"distance":0.0,"speed":0.0},{"calorie":0.0,"count":0,"distance":0.0,"speed":0.0},{"calorie":0.0,"count":0,"distance":0.0,"speed":0.0},{"calorie":0.0,"count":0,"distance":0.0,"speed":0.0},{"calorie":0.0,"count":0,"distance":0.0,"speed":0.0},{"calorie":0.4000000059604645,"count":7,"distance":6.440000057220459,"speed":6.199999809265137},{"calorie":0.0,"count":0,"distance":0.0,"speed":0.0},{"calorie":0.0,"count":0,"distance":0.0,"speed":0.0},{"calorie":0.3100000023841858,"count":9,"distance":7.15000057220459,"speed":6.018237590789795},{"calorie":0.0,"count":0,"distance":0.0,"speed":0.0},{"calorie":1.7999999523162842,"count":56,"distance":43.5099983215332,"speed":5.600000381469727},{"calorie":10.029999256134033,"count":246,"distance":171.8000030517578,"speed":4.8466105461120605},{"calorie":0.0,"count":0,"distance":0.0,"speed":0.0},{"calorie":11.429999887943268,"count":305,"distance":238.5900068283081,"speed":5.634627342224121},{"calorie":4.129999876022339,"count":121,"distance":92.52999877929688,"speed":5.33903169631958},{"calorie":0.0,"count":0,"distance":0.0,"speed":0.0},{"calorie":0.0,"count":0,"distance":0.0,"speed":0.0},{"calorie":0.0,"count":0,"distance":0.0,"speed":0.0},{"calorie":0.0,"count":0,"distance":0.0,"speed":0.0},{"calorie":0.0,"count":0,"distance":0.0,"speed":0.0},{"calorie":4.439999967813492,"count":108,"distance":89.72000026702881,"speed":5.802219867706299},{"calorie":0.0,"count":0,"distance":0.0,"speed":0.0},{"calorie":0.0,"count":0,"distance":0.0,"speed":0.0},{"calorie":0.0,"count":0,"distance":0.0,"speed":0.0},{"calorie":0.0,"count":0,"distance":0.0,"speed":0.0},{"calorie":5.8500001430511475,"count":171,"distance":134.010000705719,"speed":5.601658821105957},{"calorie":8.429999351501465,"count":226,"distance":178.40001106262207,"speed":5.395094394683838},{"calorie":2.9000000953674316,"count":86,"distance":65.5600004196167,"speed":4.9501953125},{"calorie":0.6600000262260437,"count":18,"distance":13.680000305175781,"speed":4.900000095367432},{"calorie":0.0,"count":0,"distance":0.0,"speed":0.0},{"calorie":0.0,"count":0,"distance":0.0,"speed":0.0},{"calorie":0.0,"count":0,"distance":0.0,"speed":0.0},{"calorie":1.819999873638153,"count":56,"distance":42.72999954223633,"speed":5.6167473793029785},{"calorie":0.0,"count":0,"distance":0.0,"speed":0.0},{"calorie":0.0,"count":0,"distance":0.0,"speed":0.0},{"calorie":0.0,"count":0,"distance":0.0,"speed":0.0},{"calorie":2.6699999570846558,"count":60,"distance":51.53999900817871,"speed":6.217480659484863},{"calorie":2.8499999046325684,"count":74,"distance":57.41999912261963,"speed":4.989443778991699},{"calorie":5.429999940097332,"count":169,"distance":134.77000045776367,"speed":5.95244836807251},{"calorie":3.519999921321869,"count":79,"distance":67.3899974822998,"speed":6.506842613220215},{"calorie":1.3799998760223389,"count":37,"distance":29.3799991607666,"speed":5.990799903869629},{"calorie":1.4099998474121094,"count":27,"distance":26.229997634887695,"speed":7.962798118591309},{"calorie":1.7699998617172241,"count":51,"distance":39.70000076293945,"speed":5.599900245666504},{"calorie":0.0,"count":0,"distance":0.0,"speed":0.0},{"calorie":1.3600000143051147,"count":30,"distance":27.520000457763672,"speed":8.0},{"calorie":0.0,"count":0,"distance":0.0,"speed":0.0},{"calorie":0.0,"count":0,"distance":0.0,"speed":0.0},{"calorie":0.0,"count":0,"distance":0.0,"speed":0.0},{"calorie":0.0,"count":0,"distance":0.0,"speed":0.0},{"calorie":0.0,"count":0,"distance":0.0,"speed":0.0},{"calorie":1.6300000250339508,"count":45,"distance":38.3299994468689,"speed":7.161473274230957},{"calorie":1.4299999475479126,"count":33,"distance":29.530000686645508,"speed":6.600000381469727},{"calorie":0.0,"count":0,"distance":0.0,"speed":0.0},{"calorie":0.8899999856948853,"count":23,"distance":19.09000062942505,"speed":6.122547626495361},{"calorie":0.0,"count":0,"distance":0.0,"speed":0.0},{"calorie":0.0,"count":0,"distance":0.0,"speed":0.0},{"calorie":0.0,"count":0,"distance":0.0,"speed":0.0},{"calorie":0.0,"count":0,"distance":0.0,"speed":0.0},{"calorie":0.0,"count":0,"distance":0.0,"speed":0.0},{"calorie":0.0,"count":0,"distance":0.0,"speed":0.0},{"calorie":0.0,"count":0,"distance":0.0,"speed":0.0},{"calorie":0.0,"count":0,"distance":0.0,"speed":0.0},{"calorie":0.0,"count":0,"distance":0.0,"speed":0.0},{"calorie":0.0,"count":0,"distance":0.0,"speed":0.0},{"calorie":0.0,"count":0,"distance":0.0,"speed":0.0},{"calorie":0.6400000154972076,"count":20,"distance":16.040000438690186,"speed":6.837647914886475},{"calorie":3.0600000619888306,"count":79,"distance":64.84000015258789,"speed":6.555332660675049},{"calorie":1.5999997556209564,"count":47,"distance":39.21999549865723,"speed":7.860413551330566},{"calorie":6.2200000286102295,"count":160,"distance":124.9399995803833,"speed":5.271662712097168},{"calorie":7.299999877810478,"count":203,"distance":154.04000282287598,"speed":4.971714496612549},{"calorie":0.0,"count":0,"distance":0.0,"speed":0.0},{"calorie":1.909999966621399,"count":47,"distance":37.52000045776367,"speed":5.474270343780518},{"calorie":2.589999958872795,"count":76,"distance":60.02999949455261,"speed":6.349469184875488},{"calorie":0.9300000071525574,"count":25,"distance":18.940000534057617,"speed":4.799999713897705},{"calorie":5.959999702870846,"count":154,"distance":118.92999935150146,"speed":4.8867363929748535},{"calorie":9.079999908804893,"count":265,"distance":204.28999423980713,"speed":5.254276275634766},{"calorie":0.0,"count":0,"distance":0.0,"speed":0.0},{"calorie":1.7000000178813934,"count":49,"distance":39.250001430511475,"speed":6.410192489624023},{"calorie":0.6100000143051147,"count":6,"distance":8.880000114440918,"speed":6.199999809265137},{"calorie":0.6199999749660492,"count":18,"distance":14.019999980926514,"speed":5.242802143096924},{"calorie":0.0,"count":0,"distance":0.0,"speed":0.0},{"calorie":1.409999966621399,"count":36,"distance":29.799999237060547,"speed":6.840572357177734},{"calorie":0.0,"count":0,"distance":0.0,"speed":0.0},{"calorie":0.26999998092651367,"count":8,"distance":6.390000343322754,"speed":6.809682846069336},{"calorie":0.0,"count":0,"distance":0.0,"speed":0.0},{"calorie":0.0,"count":0,"distance":0.0,"speed":0.0},{"calorie":0.0,"count":0,"distance":0.0,"speed":0.0},{"calorie":0.0,"count":0,"distance":0.0,"speed":0.0},{"calorie":3.9699990153312683,"count":107,"distance":82.94999694824219,"speed":5.653102397918701},{"calorie":0.4399999678134918,"count":12,"distance":9.0,"speed":4.1955885887146},{"calorie":1.6899998188018799,"count":53,"distance":42.099998474121094,"speed":5.883083343505859},{"calorie":0.0,"count":0,"distance":0.0,"speed":0.0},{"calorie":0.0,"count":0,"distance":0.0,"speed":0.0},{"calorie":0.30000001192092896,"count":9,"distance":7.019999980926514,"speed":5.599999904632568},{"calorie":0.4899999797344208,"count":14,"distance":10.600000381469727,"speed":4.981142520904541},{"calorie":1.3700001090765,"count":39,"distance":30.26000690460205,"speed":5.644315242767334},{"calorie":0.0,"count":0,"distance":0.0,"speed":0.0},{"calorie":0.0,"count":0,"distance":0.0,"speed":0.0},{"calorie":0.0,"count":0,"distance":0.0,"speed":0.0},{"calorie":0.0,"count":0,"distance":0.0,"speed":0.0},{"calorie":0.0,"count":0,"distance":0.0,"speed":0.0},{"calorie":0.0,"count":0,"distance":0.0,"speed":0.0}]