[{"score":39,"score_max":82,"score_min":0,"flag":1,"level":0,"start_time":1578124800000,"end_time":1578124859999},{"score":0,"score_max":0,"score_min":0,"flag":1,"level":0,"start_time":1578124860000,"end_time":1578124919999},{"score":0,"score_max":1,"score_min":0,"flag":1,"level":0,"start_time":1578124920000,"end_time":1578124979999},{"score":0,"score_max":0,"score_min":0,"flag":1,"level":0,"start_time":1578124980000,"end_time":1578125039999},{"score":0,"score_max":0,"score_min":0,"flag":1,"level":0,"start_time":1578125040000,"end_time":1578125099999},{"score":0,"score_max":0,"score_min":0,"flag":1,"level":0,"start_time":1578125100000,"end_time":1578125159999},{"score":0,"score_max":0,"score_min":0,"flag":1,"level":0,"start_time":1578125160000,"end_time":1578125219999},{"score":0,"score_max":0,"score_min":0,"flag":1,"level":0,"start_time":1578125220000,"end_time":1578125279999},{"score":0,"score_max":0,"score_min":0,"flag":1,"level":0,"start_time":1578125280000,"end_time":1578125339999},{"score":0,"score_max":0,"score_min":0,"flag":1,"level":0,"start_time":1578125340000,"end_time":1578125399999},{"score":0,"score_max":0,"score_min":0,"flag":1,"level":0,"start_time":1578125400000,"end_time":1578125459999},{"score":0,"score_max":0,"score_min":0,"flag":1,"level":0,"start_time":1578125460000,"end_time":1578125519999},{"score":12,"score_max":66,"score_min":0,"flag":1,"level":0,"start_time":1578125520000,"end_time":1578125579999},{"score":92,"score_max":98,"score_min":69,"flag":1,"level":1,"start_time":1578125580000,"end_time":1578125639999},{"score":86,"score_max":97,"score_min":63,"flag":1,"level":1,"start_time":1578125640000,"end_time":1578125699999},{"score":53,"score_max":65,"score_min":46,"flag":1,"level":0,"start_time":1578125700000,"end_time":1578125759999},{"score":91,"score_max":100,"score_min":66,"flag":1,"level":1,"start_time":1578125760000,"end_time":1578125819999},{"score":100,"score_max":100,"score_min":0,"flag":1,"level":1,"start_time":1578125820000,"end_time":1578125879999},{"score":100,"score_max":100,"score_min":0,"flag":1,"level":1,"start_time":1578125880000,"end_time":1578125939999},{"score":100,"score_max":100,"score_min":0,"flag":1,"level":1,"start_time":1578125940000,"end_time":1578125999999},{"score":100,"score_max":100,"score_min":0,"flag":1,"level":1,"start_time":1578126000000,"end_time":1578126059999},{"score":99,"score_max":100,"score_min":98,"flag":1,"level":1,"start_time":1578126060000,"end_time":1578126119999},{"score":87,"score_max":98,"score_min":69,"flag":1,"level":1,"start_time":1578126120000,"end_time":1578126179999},{"score":18,"score_max":67,"score_min":1,"flag":1,"level":0,"start_time":1578126180000,"end_time":1578126239999},{"score":8,"score_max":25,"score_min":1,"flag":1,"level":0,"start_time":1578126240000,"end_time":1578126299999},{"score":0,"score_max":6,"score_min":0,"flag":1,"level":0,"start_time":1578126300000,"end_time":1578126359999},{"score":0,"score_max":2,"score_min":0,"flag":1,"level":0,"start_time":1578126360000,"end_time":1578126419999},{"score":0,"score_max":0,"score_min":0,"flag":1,"level":0,"start_time":1578126420000,"end_time":1578126479999},{"score":0,"score_max":0,"score_min":0,"flag":1,"level":0,"start_time":1578126480000,"end_time":1578126539999},{"score":10,"score_max":40,"score_min":0,"flag":1,"level":0,"start_time":1578126540000,"end_time":1578126599999},{"score":82,"score_max":97,"score_min":42,"flag":1,"level":1,"start_time":1578126600000,"end_time":1578126659999},{"score":79,"score_max":97,"score_min":21,"flag":1,"level":1,"start_time":1578126660000,"end_time":1578126719999},{"score":1,"score_max":18,"score_min":0,"flag":1,"level":0,"start_time":1578126720000,"end_time":1578126779999},{"score":0,"score_max":0,"score_min":0,"flag":1,"level":0,"start_time":1578126780000,"end_time":1578126839999},{"score":0,"score_max":0,"score_min":0,"flag":1,"level":0,"start_time":1578126840000,"end_time":1578126899999},{"score":0,"score_max":0,"score_min":0,"flag":1,"level":0,"start_time":1578126900000,"end_time":1578126959999},{"score":0,"score_max":0,"score_min":0,"flag":1,"level":0,"start_time":1578126960000,"end_time":1578127019999},{"score":0,"score_max":0,"score_min":0,"flag":1,"level":0,"start_time":1578127020000,"end_time":1578127079999},{"score":1,"score_max":4,"score_min":0,"flag":1,"level":0,"start_time":1578127080000,"end_time":1578127139999},{"score":1,"score_max":3,"score_min":0,"flag":1,"level":0,"start_time":1578127140000,"end_time":1578127199999},{"score":0,"score_max":0,"score_min":0,"flag":1,"level":0,"start_time":1578127200000,"end_time":1578127259999},{"score":0,"score_max":1,"score_min":0,"flag":1,"level":0,"start_time":1578127260000,"end_time":1578127319999},{"score":0,"score_max":1,"score_min":0,"flag":1,"level":0,"start_time":1578127320000,"end_time":1578127379999},{"score":0,"score_max":0,"score_min":0,"flag":1,"level":0,"start_time":1578127380000,"end_time":1578127439999},{"score":0,"score_max":0,"score_min":0,"flag":1,"level":0,"start_time":1578127440000,"end_time":1578127499999},{"score":0,"score_max":0,"score_min":0,"flag":1,"level":0,"start_time":1578127500000,"end_time":1578127559999},{"score":0,"score_max":0,"score_min":0,"flag":1,"level":0,"start_time":1578127560000,"end_time":1578127619999},{"score":0,"score_max":1,"score_min":0,"flag":1,"level":0,"start_time":1578127620000,"end_time":1578127679999},{"score":23,"score_max":56,"score_min":1,"flag":1,"level":0,"start_time":1578127680000,"end_time":1578127739999},{"score":25,"score_max":54,"score_min":0,"flag":1,"level":0,"start_time":1578127740000,"end_time":1578127799999},{"score":0,"score_max":0,"score_min":0,"flag":1,"level":0,"start_time":1578127800000,"end_time":1578127859999},{"score":0,"score_max":0,"score_min":0,"flag":1,"level":0,"start_time":1578127860000,"end_time":1578127919999},{"score":0,"score_max":0,"score_min":0,"flag":1,"level":0,"start_time":1578127920000,"end_time":1578127979999},{"score":0,"score_max":0,"score_min":0,"flag":1,"level":0,"start_time":1578127980000,"end_time":1578128039999},{"score":0,"score_max":0,"score_min":0,"flag":1,"level":0,"start_time":1578128040000,"end_time":1578128099999},{"score":0,"score_max":2,"score_min":0,"flag":1,"level":0,"start_time":1578128100000,"end_time":1578128159999},{"score":6,"score_max":22,"score_min":1,"flag":1,"level":0,"start_time":1578128160000,"end_time":1578128219999},{"score":21,"score_max":29,"score_min":17,"flag":1,"level":0,"start_time":1578128220000,"end_time":1578128279999},{"score":51,"score_max":59,"score_min":31,"flag":1,"level":0,"start_time":1578128280000,"end_time":1578128339999},{"score":74,"score_max":97,"score_min":55,"flag":1,"level":0,"start_time":1578128340000,"end_time":1578128399999}]