[{"heart_rate":72.0,"heart_rate_max":78.0,"heart_rate_min":64.0,"start_time":1575608400000,"end_time":1575608459000},{"heart_rate":75.0,"heart_rate_max":77.0,"heart_rate_min":74.0,"start_time":1575608460000,"end_time":1575608519000},{"heart_rate":79.0,"heart_rate_max":83.0,"heart_rate_min":77.0,"start_time":1575608520000,"end_time":1575608579000},{"heart_rate":82.0,"heart_rate_max":85.0,"heart_rate_min":81.0,"start_time":1575608580000,"end_time":1575608639000},{"heart_rate":85.0,"heart_rate_max":88.0,"heart_rate_min":82.0,"start_time":1575608640000,"end_time":1575608699000},{"heart_rate":87.0,"heart_rate_max":91.0,"heart_rate_min":83.0,"start_time":1575608700000,"end_time":1575608759000},{"heart_rate":84.0,"heart_rate_max":88.0,"heart_rate_min":79.0,"start_time":1575608760000,"end_time":1575608819000},{"heart_rate":85.0,"heart_rate_max":91.0,"heart_rate_min":79.0,"start_time":1575608820000,"end_time":1575608879000},{"heart_rate":88.0,"heart_rate_max":93.0,"heart_rate_min":82.0,"start_time":1575608880000,"end_time":1575608939000},{"heart_rate":68.0,"heart_rate_max":82.0,"heart_rate_min":62.0,"start_time":1575608940000,"end_time":1575608999000},{"heart_rate":71.0,"heart_rate_max":78.0,"heart_rate_min":66.0,"start_time":1575609000000,"end_time":1575609059000},{"heart_rate":79.0,"heart_rate_max":93.0,"heart_rate_min":69.0,"start_time":1575609060000,"end_time":1575609119000},{"heart_rate":87.0,"heart_rate_max":89.0,"heart_rate_min":86.0,"start_time":1575609120000,"end_time":1575609179000},{"heart_rate":81.0,"heart_rate_max":85.0,"heart_rate_min":77.0,"start_time":1575609180000,"end_time":1575609239000},{"heart_rate":78.0,"heart_rate_max":83.0,"heart_rate_min":76.0,"start_time":1575609240000,"end_time":1575609299000},{"heart_rate":74.0,"heart_rate_max":80.0,"heart_rate_min":72.0,"start_time":1575609300000,"end_time":1575609359000},{"heart_rate":69.0,"heart_rate_max":75.0,"heart_rate_min":65.0,"start_time":1575609360000,"end_time":1575609419000},{"heart_rate":66.0,"heart_rate_max":71.0,"heart_rate_min":62.0,"start_time":1575609420000,"end_time":1575609479000},{"heart_rate":74.0,"heart_rate_max":85.0,"heart_rate_min":69.0,"start_time":1575609480000,"end_time":1575609539000},{"heart_rate":88.0,"heart_rate_max":92.0,"heart_rate_min":85.0,"start_time":1575609540000,"end_time":1575609599000},{"heart_rate":88.0,"heart_rate_max":92.0,"heart_rate_min":85.0,"start_time":1575609600000,"end_time":1575609659000},{"heart_rate":88.0,"heart_rate_max":91.0,"heart_rate_min":86.0,"start_time":1575609660000,"end_time":1575609719000},{"heart_rate":88.0,"heart_rate_max":90.0,"heart_rate_min":87.0,"start_time":1575609720000,"end_time":1575609779000},{"heart_rate":89.0,"heart_rate_max":92.0,"heart_rate_min":86.0,"start_time":1575609780000,"end_time":1575609839000},{"heart_rate":88.0,"heart_rate_max":92.0,"heart_rate_min":87.0,"start_time":1575609840000,"end_time":1575609899000},{"heart_rate":94.0,"heart_rate_max":101.0,"heart_rate_min":91.0,"start_time":1575609900000,"end_time":1575609959000},{"heart_rate":99.0,"heart_rate_max":104.0,"heart_rate_min":96.0,"start_time":1575609960000,"end_time":1575610019000},{"heart_rate":85.0,"heart_rate_max":98.0,"heart_rate_min":78.0,"start_time":1575610020000,"end_time":1575610079000},{"heart_rate":78.0,"heart_rate_max":85.0,"heart_rate_min":72.0,"start_time":1575610080000,"end_time":1575610139000},{"heart_rate":69.0,"heart_rate_max":74.0,"heart_rate_min":64.0,"start_time":1575610140000,"end_time":1575610199000},{"heart_rate":67.0,"heart_rate_max":76.0,"heart_rate_min":64.0,"start_time":1575610200000,"end_time":1575610259000},{"heart_rate":81.0,"heart_rate_max":86.0,"heart_rate_min":77.0,"start_time":1575610260000,"end_time":1575610319000},{"heart_rate":83.0,"heart_rate_max":86.0,"heart_rate_min":79.0,"start_time":1575610320000,"end_time":1575610379000},{"heart_rate":73.0,"heart_rate_max":83.0,"heart_rate_min":66.0,"start_time":1575610380000,"end_time":1575610439000},{"heart_rate":72.0,"heart_rate_max":78.0,"heart_rate_min":68.0,"start_time":1575610440000,"end_time":1575610499000},{"heart_rate":70.0,"heart_rate_max":76.0,"heart_rate_min":65.0,"start_time":1575610500000,"end_time":1575610559000},{"heart_rate":72.0,"heart_rate_max":76.0,"heart_rate_min":67.0,"start_time":1575610560000,"end_time":1575610619000},{"heart_rate":71.0,"heart_rate_max":75.0,"heart_rate_min":66.0,"start_time":1575610620000,"end_time":1575610679000},{"heart_rate":69.0,"heart_rate_max":76.0,"heart_rate_min":63.0,"start_time":1575610680000,"end_time":1575610739000},{"heart_rate":69.0,"heart_rate_max":77.0,"heart_rate_min":61.0,"start_time":1575610740000,"end_time":1575610799000},{"heart_rate":69.0,"heart_rate_max":71.0,"heart_rate_min":69.0,"start_time":1575610800000,"end_time":1575610859000},{"heart_rate":67.0,"heart_rate_max":72.0,"heart_rate_min":61.0,"start_time":1575610860000,"end_time":1575610919000},{"heart_rate":62.0,"heart_rate_max":70.0,"heart_rate_min":57.0,"start_time":1575610920000,"end_time":1575610979000},{"heart_rate":60.0,"heart_rate_max":63.0,"heart_rate_min":57.0,"start_time":1575610980000,"end_time":1575611039000},{"heart_rate":57.0,"heart_rate_max":61.0,"heart_rate_min":56.0,"start_time":1575611040000,"end_time":1575611099000},{"heart_rate":60.0,"heart_rate_max":62.0,"heart_rate_min":58.0,"start_time":1575611100000,"end_time":1575611159000},{"heart_rate":59.0,"heart_rate_max":62.0,"heart_rate_min":57.0,"start_time":1575611160000,"end_time":1575611219000},{"heart_rate":74.0,"heart_rate_max":89.0,"heart_rate_min":59.0,"start_time":1575611220000,"end_time":1575611279000},{"heart_rate":76.0,"heart_rate_max":90.0,"heart_rate_min":65.0,"start_time":1575611280000,"end_time":1575611339000},{"heart_rate":65.0,"heart_rate_max":72.0,"heart_rate_min":60.0,"start_time":1575611340000,"end_time":1575611399000},{"heart_rate":74.0,"heart_rate_max":81.0,"heart_rate_min":70.0,"start_time":1575611400000,"end_time":1575611459000},{"heart_rate":73.0,"heart_rate_max":83.0,"heart_rate_min":63.0,"start_time":1575611460000,"end_time":1575611519000},{"heart_rate":67.0,"heart_rate_max":71.0,"heart_rate_min":65.0,"start_time":1575611520000,"end_time":1575611579000},{"heart_rate":70.0,"heart_rate_max":76.0,"heart_rate_min":66.0,"start_time":1575611580000,"end_time":1575611639000},{"heart_rate":77.0,"heart_rate_max":82.0,"heart_rate_min":74.0,"start_time":1575611640000,"end_time":1575611699000},{"heart_rate":73.0,"heart_rate_max":75.0,"heart_rate_min":72.0,"start_time":1575611700000,"end_time":1575611759000},{"heart_rate":74.0,"heart_rate_max":78.0,"heart_rate_min":71.0,"start_time":1575611760000,"end_time":1575611819000},{"heart_rate":76.0,"heart_rate_max":80.0,"heart_rate_min":74.0,"start_time":1575611820000,"end_time":1575611879000},{"heart_rate":74.0,"heart_rate_max":81.0,"heart_rate_min":69.0,"start_time":1575611880000,"end_time":1575611939000},{"heart_rate":76.0,"heart_rate_max":81.0,"heart_rate_min":72.0,"start_time":1575611940000,"end_time":1575611999000}]